MANIFEST.in
README.md
setup.cfg
setup.py
pryme/__init__.py
pryme/core.py
pryme/decorators.py
pryme.egg-info/PKG-INFO
pryme.egg-info/SOURCES.txt
pryme.egg-info/dependency_links.txt
pryme.egg-info/not-zip-safe
pryme.egg-info/top_level.txt