Metadata-Version: 1.0
Name: pryme
Version: 0.2
Summary: A number theory package
Home-page: http://github.com/calamitizer/pryme
Author: J. Alex Ruble
Author-email: jaruble@ncsu.edu
License: MIT
Platform: UNKNOWN
